AD2020/AD2020.py
AD2020/AD2020Fun.py
AD2020/AD2020Root.py
AD2020/__init__.py
tests/__init__.py
tests/test_AD2020.py
tests/test_AD2020Fun.py
tests/test_AD2020Root.py
AD2020-0.0.2.dist-info/LICENSE
AD2020-0.0.2.dist-info/METADATA
AD2020-0.0.2.dist-info/WHEEL
AD2020-0.0.2.dist-info/top_level.txt
AD2020-0.0.2.dist-info/RECORD
